assignment_tool/__init__.py
assignment_tool/app.py
assignment_tool/assignment_screen.kv
assignment_tool/assignment_screen.py
assignment_tool/assignmenttool.kv
assignment_tool/details_screen.kv
assignment_tool/details_screen.py
assignment_tool/hotReloader.py
assignment_tool/manager.py
assignment_tool/profile_screen.kv
assignment_tool/profile_screen.py
assignment_tool/result_screen.kv
assignment_tool/result_screen.py
assignment_tool/result_text.py
assignment_tool/splash_screen.kv
assignment_tool/splash_screen.py
assignment_tool/textfields.py
assignment_tool/utils.py
assignment_tool/assets/Pacifico-Regular.ttf
assignment_tool/assets/UbuntuMono-Regular.ttf
assignment_tool/assets/create.txt
assignment_tool/assets/index.html
assignment_tool/assets/logo-gen.gif
assignment_tool/assets/logo.gif
assignment_tool/assets/logo.png
assignment_tool/assets/logo128.ico
assignment_tool/assets/logo128.png
assignment_tool/assets/logo16.ico
assignment_tool/assets/logo16.png
assignment_tool/assets/logo24.ico
assignment_tool/assets/logo24.png
assignment_tool/assets/logo255.ico
assignment_tool/assets/logo255.png
assignment_tool/assets/logo32.ico
assignment_tool/assets/logo32.png
assignment_tool/assets/logo48.ico
assignment_tool/assets/logo48.png
assignment_tool/assets/logo64.ico
assignment_tool/assets/logo64.png
assignment_tool/assets/vscode/tasks.json
assignment_tool/assets/vscode/tasks_default.json
assignment_tool_sebastian_stigler-1.6.0.dist-info/LICENSE
assignment_tool_sebastian_stigler-1.6.0.dist-info/METADATA
assignment_tool_sebastian_stigler-1.6.0.dist-info/WHEEL
assignment_tool_sebastian_stigler-1.6.0.dist-info/entry_points.txt
assignment_tool_sebastian_stigler-1.6.0.dist-info/top_level.txt
assignment_tool_sebastian_stigler-1.6.0.dist-info/RECORD
