Metadata-Version: 2.1
Name: assignment-tool-sebastian-stigler
Version: 1.6.0
Summary: Tool to manage the assignments in the VM.
Home-page: https://in-stigler.htw-aalen.de/gitea/tools/assignment_tool
Author: Sebastian Stigler
Author-email: sebastian.stigler@hs-aalen.de
Classifier: Intended Audience :: Education
Classifier: Programming Language :: Python :: 3
Classifier: Programming Language :: Python :: 3.8
Classifier: License :: OSI Approved :: MIT License
Classifier: Operating System :: POSIX :: Linux
Requires-Python: >=3.8
License-File: LICENSE
Requires-Dist: Kivy ==2.0.0
Requires-Dist: Kivy-Garden ==0.1.4
Requires-Dist: kivymd ==0.104.2
Requires-Dist: Pillow ==9.0.1
Requires-Dist: Pygments ==2.11.2
Requires-Dist: requests ==2.27.1
Requires-Dist: requests-toolbelt ==0.9.1
Requires-Dist: dataclasses-json ==0.5.7
